solidctf/__init__.py
solidctf/config.py
solidctf/ethereum.py
solidctf/service.py
solidctf/ui.py
solidctf/protobuf/challenge.proto
solidctf-1.0.0.dist-info/LICENSE
solidctf-1.0.0.dist-info/WHEEL
solidctf-1.0.0.dist-info/METADATA
solidctf-1.0.0.dist-info/RECORD
