Metadata-Version: 2.1
Name: solidctf
Version: 1.0.0
Summary: SolidCTF is an infrastructure solution that simplifies the build of Solidity CTF challenges.
Author: chainflag
Classifier: License :: OSI Approved :: MIT License
